tp_generator/AttackTypes.py
tp_generator/Bruteforcer_List.py
tp_generator/MFA_Generator.py
tp_generator/Nonce_Generator.py
tp_generator/QR_Generator.py
tp_generator/Utils.py
tp_generator/__init__.py
tp_generator-2025.10.7.dist-info/LICENSE
tp_generator-2025.10.7.dist-info/METADATA
tp_generator-2025.10.7.dist-info/WHEEL
tp_generator-2025.10.7.dist-info/top_level.txt
tp_generator-2025.10.7.dist-info/RECORD
