Metadata-Version: 2.1
Name: tp-generator
Version: 2025.10.7
Author-email: TP Cyber Security <tpcybersec2023@gmail.com>
License: MIT
Project-URL: Homepage, https://github.com/TPCyberSec/TP-Generator
Keywords: TPCyberSec,TP-Generator
Classifier: Programming Language :: Python :: 3
Classifier: Programming Language :: Python :: Implementation :: Jython
License-File: LICENSE
Requires-Dist: json-duplicate-keys>=2025.9.30
